{"format":2,"version":"5.5","globals":"c77bc06ab56be82129bafbc2f52ac0a0","files":{"application___init___py":{"hash":"102d098423646e19a10bef68efa28637","index":{"nums":[1,8,0,0,0,0,0],"html_filename":"application___init___py.html","relative_filename":"application/__init__.py"}},"application_forms_py":{"hash":"b4cd15c7d57e0a2d31f8cbc6fff66ed4","index":{"nums":[1,31,0,0,0,0,0],"html_filename":"application_forms_py.html","relative_filename":"application/forms.py"}},"application_models_py":{"hash":"5b3a1c739aa862d4efd5bce1680aa317","index":{"nums":[1,31,0,0,0,0,0],"html_filename":"application_models_py.html","relative_filename":"application/models.py"}},"application_routes_py":{"hash":"2eed749ff6a0addaf02f59b25989dfd3","index":{"nums":[1,235,0,210,0,0,0],"html_filename":"application_routes_py.html","relative_filename":"application/routes.py"}}}}